LICENSE
MANIFEST.in
README.md
setup.py
pycorrector/__init__.py
pycorrector/__main__.py
pycorrector/confusion_corrector.py
pycorrector/corrector.py
pycorrector/detector.py
pycorrector/en_spell_corrector.py
pycorrector/proper_corrector.py
pycorrector/version.py
pycorrector.egg-info/PKG-INFO
pycorrector.egg-info/SOURCES.txt
pycorrector.egg-info/dependency_links.txt
pycorrector.egg-info/not-zip-safe
pycorrector.egg-info/requires.txt
pycorrector.egg-info/top_level.txt
pycorrector/data/common_char_set.txt
pycorrector/data/en.json.gz
pycorrector/data/person_name.txt
pycorrector/data/place_name.txt
pycorrector/data/proper_name.txt
pycorrector/data/same_pinyin.txt
pycorrector/data/same_stroke.txt
pycorrector/data/sighan2015_test.tsv
pycorrector/data/stopwords.txt
pycorrector/data/stroke.txt
pycorrector/data/word_freq.txt
pycorrector/deepcontext/__init__.py
pycorrector/deepcontext/deepcontext_corrector.py
pycorrector/deepcontext/deepcontext_model.py
pycorrector/deepcontext/deepcontext_utils.py
pycorrector/ernie_csc/__init__.py
pycorrector/ernie_csc/ernie_csc_corrector.py
pycorrector/ernie_csc/model.py
pycorrector/ernie_csc/predict.py
pycorrector/ernie_csc/sighan_evaluate.py
pycorrector/ernie_csc/utils.py
pycorrector/gpt/__init__.py
pycorrector/gpt/gpt_corrector.py
pycorrector/gpt/gpt_model.py
pycorrector/gpt/gpt_utils.py
pycorrector/gpt/merge_peft_adapter.py
pycorrector/macbert/__init__.py
pycorrector/macbert/base_model.py
pycorrector/macbert/defaults.py
pycorrector/macbert/evaluate_util.py
pycorrector/macbert/lr_scheduler.py
pycorrector/macbert/macbert4csc.py
pycorrector/macbert/macbert_corrector.py
pycorrector/macbert/reader.py
pycorrector/macbert/softmaskedbert4csc.py
pycorrector/mucgec_bart/__init__.py
pycorrector/mucgec_bart/monkey_pack.py
pycorrector/mucgec_bart/mucgec_bart_corrector.py
pycorrector/nasgec_bart/__init__.py
pycorrector/nasgec_bart/nasgec_bart_corrector.py
pycorrector/seq2seq/__init__.py
pycorrector/seq2seq/conv_seq2seq_corrector.py
pycorrector/seq2seq/conv_seq2seq_model.py
pycorrector/seq2seq/conv_seq2seq_utils.py
pycorrector/t5/__init__.py
pycorrector/t5/t5_corrector.py
pycorrector/utils/__init__.py
pycorrector/utils/error_utils.py
